embedding_atlas/__init__.py
embedding_atlas/cli.py
embedding_atlas/data_source.py
embedding_atlas/options.py
embedding_atlas/projection.py
embedding_atlas/server.py
embedding_atlas/streamlit.py
embedding_atlas/utils.py
embedding_atlas/version.py
embedding_atlas/widget.py
embedding_atlas/static/index.html
embedding_atlas/static/assets/clustering.worker-BJJ4BtQg.js
embedding_atlas/static/assets/duckdb-browser-eh.worker-DcYAbAi8.js
embedding_atlas/static/assets/duckdb-browser-mvp.worker-Bc8GfOvd.js
embedding_atlas/static/assets/duckdb-eh-CAt5YSMB.wasm
embedding_atlas/static/assets/duckdb-mvp-C5CQ5aRn.wasm
embedding_atlas/static/assets/embedding.worker-DkHRd1JM.js
embedding_atlas/static/assets/index-B7rbA_Q4.css
embedding_atlas/static/assets/index-CJyOtoRm.js
embedding_atlas/static/assets/javascript-ySlJ1b_l.js
embedding_atlas/static/assets/ort-wasm-simd-threaded.jsep-B0T3yYHD.wasm
embedding_atlas/static/assets/search.worker-t1sBWce_.js
embedding_atlas/static/assets/vitesse-dark-D0r3Knsf.js
embedding_atlas/static/assets/vitesse-light-CVO1_9PV.js
embedding_atlas/static/duckdb-wasm/v1.3.2/wasm_eh/fts.duckdb_extension.wasm
embedding_atlas/static/duckdb-wasm/v1.3.2/wasm_eh/json.duckdb_extension.wasm
embedding_atlas/static/duckdb-wasm/v1.3.2/wasm_eh/parquet.duckdb_extension.wasm
embedding_atlas/static/duckdb-wasm/v1.3.2/wasm_mvp/fts.duckdb_extension.wasm
embedding_atlas/static/duckdb-wasm/v1.3.2/wasm_mvp/json.duckdb_extension.wasm
embedding_atlas/static/duckdb-wasm/v1.3.2/wasm_mvp/parquet.duckdb_extension.wasm
embedding_atlas/widget_static/anywidget/index.js
embedding_atlas/widget_static/streamlit/index.html
embedding_atlas/widget_static/streamlit/assets/chunk-CcmG315c-CVO1_9PV.js
embedding_atlas/widget_static/streamlit/assets/chunk-Cym-eLtO-D0r3Knsf.js
embedding_atlas/widget_static/streamlit/assets/chunk-fa8UlHZE-ySlJ1b_l.js
embedding_atlas/widget_static/streamlit/assets/clustering.worker-1H2WZlBX.js
embedding_atlas/widget_static/streamlit/assets/index-BpJFCoXd.js
embedding_atlas-0.16.1.dist-info/METADATA
embedding_atlas-0.16.1.dist-info/WHEEL
embedding_atlas-0.16.1.dist-info/entry_points.txt
embedding_atlas-0.16.1.dist-info/RECORD
